{"ala_frontend":{"titolo":"ezstring 20","struttura_di_riferimento":"ezobjectrelationlist 19","utente":"ezobjectrelationlist 20","matricola":"ezstring 0","ruolo":"ezstring 0","descrizione_ruolo_speciale":"ezstring 0","data_inizio_attivita":"ezdate 0","data_fine_attivita":"ezdate 0","_NumeroOggetti":"20"},"aldeno_frontend":{"titolo":"ezstring 14","struttura_di_riferimento":"ezobjectrelationlist 11","utente":"ezobjectrelationlist 14","matricola":"ezstring 0","ruolo":"ezstring 0","descrizione_ruolo_speciale":"ezstring 0","data_inizio_attivita":"ezdate 0","data_fine_attivita":"ezdate 0","_NumeroOggetti":"11"},"amblar_frontend":{"titolo":"ezstring 1","struttura_di_riferimento":"ezobjectrelationlist 0","utente":"ezobjectrelationlist 1","matricola":"ezstring 0","ruolo":"ezstring 0","descrizione_ruolo_speciale":"ezstring 0","data_inizio_attivita":"ezdate 0","data_fine_attivita":"ezdate 0","_NumeroOggetti":"1"},"arco_frontend":{"titolo":"ezstring 57","struttura_di_riferimento":"ezobjectrelationlist 56","utente":"ezobjectrelationlist 53","matricola":"ezstring 0","ruolo":"ezstring 0","descrizione_ruolo_speciale":"ezstring 0","data_inizio_attivita":"ezdate 0","data_fine_attivita":"ezdate 0","_NumeroOggetti":"57"},"avio_frontend":{"titolo":"ezstring 5","struttura_di_riferimento":"ezobjectrelationlist 3","utente":"ezobjectrelationlist 4","matricola":"ezstring 0","ruolo":"ezstring 0","descrizione_ruolo_speciale":"ezstring 0","data_inizio_attivita":"ezdate 0","data_fine_attivita":"ezdate 0","_NumeroOggetti":"1"},"baselgapine_frontend":{"titolo":"ezstring 13","struttura_di_riferimento":"ezobjectrelationlist 13","utente":"ezobjectrelationlist 13","matricola":"ezstring 0","ruolo":"ezstring 0","descrizione_ruolo_speciale":"ezstring 0","data_inizio_attivita":"ezdate 0","data_fine_attivita":"ezdate 0","_NumeroOggetti":"12"},"bersone_frontend":{"titolo":"ezstring 1","struttura_di_riferimento":"ezobjectrelationlist 0","utente":"ezobjectrelationlist 1","matricola":"ezstring 0","ruolo":"ezstring 0","descrizione_ruolo_speciale":"ezstring 0","data_inizio_attivita":"ezdate 0","data_fine_attivita":"ezdate 0","_NumeroOggetti":"1"},"bolbeno_frontend":{"titolo":"ezstring 0","struttura_di_riferimento":"ezobjectrelationlist 0","utente":"ezobjectrelationlist 0","matricola":"ezstring 0","ruolo":"ezstring 0","descrizione_ruolo_speciale":"ezstring 0","data_inizio_attivita":"ezdate 0","data_fine_attivita":"ezdate 0","_NumeroOggetti":"0"},"bondo_frontend":{"titolo":"ezstring 1","struttura_di_riferimento":"ezobjectrelationlist 0","utente":"ezobjectrelationlist 1","matricola":"ezstring 0","ruolo":"ezstring 0","descrizione_ruolo_speciale":"ezstring 0","data_inizio_attivita":"ezdate 0","data_fine_attivita":"ezdate 0","_NumeroOggetti":"1"},"bondone_frontend":{"titolo":"ezstring 1","struttura_di_riferimento":"ezobjectrelationlist 0","utente":"ezobjectrelationlist 1","matricola":"ezstring 0","ruolo":"ezstring 0","descrizione_ruolo_speciale":"ezstring 0","data_inizio_attivita":"ezdate 0","data_fine_attivita":"ezdate 0","_NumeroOggetti":"1"},"bosentino_frontend":{"titolo":"ezstring 7","struttura_di_riferimento":"ezobjectrelationlist 7","utente":"ezobjectrelationlist 7","matricola":"ezstring 0","ruolo":"ezstring 0","descrizione_ruolo_speciale":"ezstring 0","data_inizio_attivita":"ezdate 0","data_fine_attivita":"ezdate 0","_NumeroOggetti":"7"},"bresimo_frontend":{"titolo":"ezstring 1","struttura_di_riferimento":"ezobjectrelationlist 1","utente":"ezobjectrelationlist 1","matricola":"ezstring 0","ruolo":"ezstring 0","descrizione_ruolo_speciale":"ezstring 0","data_inizio_attivita":"ezdate 0","data_fine_attivita":"ezdate 0","_NumeroOggetti":"1"},"brione_frontend":{"titolo":"ezstring 2","struttura_di_riferimento":"ezobjectrelationlist 1","utente":"ezobjectrelationlist 2","matricola":"ezstring 0","ruolo":"ezstring 0","descrizione_ruolo_speciale":"ezstring 0","data_inizio_attivita":"ezdate 0","data_fine_attivita":"ezdate 0","_NumeroOggetti":"2"},"cagno_frontend":{"titolo":"ezstring 1","struttura_di_riferimento":"ezobjectrelationlist 1","utente":"ezobjectrelationlist 1","matricola":"ezstring 0","ruolo":"ezstring 0","descrizione_ruolo_speciale":"ezstring 0","data_inizio_attivita":"ezdate 0","data_fine_attivita":"ezdate 0","_NumeroOggetti":"1"},"caldes_frontend":{"titolo":"ezstring 4","struttura_di_riferimento":"ezobjectrelationlist 3","utente":"ezobjectrelationlist 4","matricola":"ezstring 0","ruolo":"ezstring 0","descrizione_ruolo_speciale":"ezstring 0","data_inizio_attivita":"ezdate 0","data_fine_attivita":"ezdate 0","_NumeroOggetti":"3"},"calliano_frontend":{"titolo":"ezstring 1","struttura_di_riferimento":"ezobjectrelationlist 1","utente":"ezobjectrelationlist 1","matricola":"ezstring 0","ruolo":"ezstring 0","descrizione_ruolo_speciale":"ezstring 0","data_inizio_attivita":"ezdate 0","data_fine_attivita":"ezdate 0","_NumeroOggetti":"1"},"campitello_frontend":{"titolo":"ezstring 0","struttura_di_riferimento":"ezobjectrelationlist 0","utente":"ezobjectrelationlist 0","matricola":"ezstring 0","ruolo":"ezstring 0","descrizione_ruolo_speciale":"ezstring 0","data_inizio_attivita":"ezdate 0","data_fine_attivita":"ezdate 0","_NumeroOggetti":"0"},"carano_frontend":{"titolo":"ezstring 6","struttura_di_riferimento":"ezobjectrelationlist 5","utente":"ezobjectrelationlist 6","matricola":"ezstring 0","ruolo":"ezstring 0","descrizione_ruolo_speciale":"ezstring 0","data_inizio_attivita":"ezdate 0","data_fine_attivita":"ezdate 0","_NumeroOggetti":"5"},"carisolo_frontend":{"titolo":"ezstring 21","struttura_di_riferimento":"ezobjectrelationlist 20","utente":"ezobjectrelationlist 21","matricola":"ezstring 0","ruolo":"ezstring 0","descrizione_ruolo_speciale":"ezstring 0","data_inizio_attivita":"ezdate 0","data_fine_attivita":"ezdate 0","_NumeroOggetti":"20"},"castelcondino_frontend":{"titolo":"ezstring 1","struttura_di_riferimento":"ezobjectrelationlist 0","utente":"ezobjectrelationlist 1","matricola":"ezstring 0","ruolo":"ezstring 0","descrizione_ruolo_speciale":"ezstring 0","data_inizio_attivita":"ezdate 0","data_fine_attivita":"ezdate 0","_NumeroOggetti":"1"},"castelfondo_frontend":{"titolo":"ezstring 3","struttura_di_riferimento":"ezobjectrelationlist 1","utente":"ezobjectrelationlist 3","matricola":"ezstring 0","ruolo":"ezstring 0","descrizione_ruolo_speciale":"ezstring 0","data_inizio_attivita":"ezdate 0","data_fine_attivita":"ezdate 0","_NumeroOggetti":"1"},"castellomolina_frontend":{"titolo":"ezstring 1","struttura_di_riferimento":"ezobjectrelationlist 0","utente":"ezobjectrelationlist 1","matricola":"ezstring 0","ruolo":"ezstring 0","descrizione_ruolo_speciale":"ezstring 0","data_inizio_attivita":"ezdate 0","data_fine_attivita":"ezdate 0","_NumeroOggetti":"1"},"cavalese_frontend":{"titolo":"ezstring 14","struttura_di_riferimento":"ezobjectrelationlist 14","utente":"ezobjectrelationlist 14","matricola":"ezstring 0","ruolo":"ezstring 0","descrizione_ruolo_speciale":"ezstring 0","data_inizio_attivita":"ezdate 0","data_fine_attivita":"ezdate 0","_NumeroOggetti":"14"},"cavizzana_frontend":{"titolo":"ezstring 5","struttura_di_riferimento":"ezobjectrelationlist 4","utente":"ezobjectrelationlist 5","matricola":"ezstring 0","ruolo":"ezstring 0","descrizione_ruolo_speciale":"ezstring 0","data_inizio_attivita":"ezdate 0","data_fine_attivita":"ezdate 0","_NumeroOggetti":"5"},"centasannicolo_frontend":{"titolo":"ezstring 4","struttura_di_riferimento":"ezobjectrelationlist 3","utente":"ezobjectrelationlist 4","matricola":"ezstring 0","ruolo":"ezstring 0","descrizione_ruolo_speciale":"ezstring 0","data_inizio_attivita":"ezdate 0","data_fine_attivita":"ezdate 0","_NumeroOggetti":"4"},"cimego_frontend":{"titolo":"ezstring 0","struttura_di_riferimento":"ezobjectrelationlist 0","utente":"ezobjectrelationlist 0","matricola":"ezstring 0","ruolo":"ezstring 0","descrizione_ruolo_speciale":"ezstring 0","data_inizio_attivita":"ezdate 0","data_fine_attivita":"ezdate 0","_NumeroOggetti":"0"},"cles_frontend":{"titolo":"ezstring 9","struttura_di_riferimento":"ezobjectrelationlist 8","utente":"ezobjectrelationlist 9","matricola":"ezstring 0","ruolo":"ezstring 0","descrizione_ruolo_speciale":"ezstring 0","data_inizio_attivita":"ezdate 0","data_fine_attivita":"ezdate 0","_NumeroOggetti":"8"},"commezzadura_frontend":{"titolo":"ezstring 9","struttura_di_riferimento":"ezobjectrelationlist 8","utente":"ezobjectrelationlist 9","matricola":"ezstring 0","ruolo":"ezstring 0","descrizione_ruolo_speciale":"ezstring 0","data_inizio_attivita":"ezdate 0","data_fine_attivita":"ezdate 0","_NumeroOggetti":"6"},"comunetest_frontend":{"titolo":"ezstring 0","struttura_di_riferimento":"ezobjectrelationlist 0","utente":"ezobjectrelationlist 0","matricola":"ezstring 0","ruolo":"ezstring 0","descrizione_ruolo_speciale":"ezstring 0","data_inizio_attivita":"ezdate 0","data_fine_attivita":"ezdate 0","_NumeroOggetti":"0"},"condino_frontend":{"titolo":"ezstring 5","struttura_di_riferimento":"ezobjectrelationlist 4","utente":"ezobjectrelationlist 5","matricola":"ezstring 0","ruolo":"ezstring 0","descrizione_ruolo_speciale":"ezstring 0","data_inizio_attivita":"ezdate 0","data_fine_attivita":"ezdate 0","_NumeroOggetti":"5"},"consorzio_frontend":{"titolo":"ezstring 0","struttura_di_riferimento":"ezobjectrelationlist 0","utente":"ezobjectrelationlist 0","matricola":"ezstring 0","ruolo":"ezstring 0","descrizione_ruolo_speciale":"ezstring 0","data_inizio_attivita":"ezdate 0","data_fine_attivita":"ezdate 0","_NumeroOggetti":"0"},"consorzioinnovazione_frontend":{"titolo":"ezstring 0","struttura_di_riferimento":"ezobjectrelationlist 0","utente":"ezobjectrelationlist 0","matricola":"ezstring 0","ruolo":"ezstring 0","descrizione_ruolo_speciale":"ezstring 0","data_inizio_attivita":"ezdate 0","data_fine_attivita":"ezdate 0","_NumeroOggetti":"0"},"cunevo_frontend":{"titolo":"ezstring 4","struttura_di_riferimento":"ezobjectrelationlist 3","utente":"ezobjectrelationlist 4","matricola":"ezstring 0","ruolo":"ezstring 0","descrizione_ruolo_speciale":"ezstring 0","data_inizio_attivita":"ezdate 0","data_fine_attivita":"ezdate 0","_NumeroOggetti":"3"},"daiano_frontend":{"titolo":"ezstring 1","struttura_di_riferimento":"ezobjectrelationlist 0","utente":"ezobjectrelationlist 1","matricola":"ezstring 0","ruolo":"ezstring 0","descrizione_ruolo_speciale":"ezstring 0","data_inizio_attivita":"ezdate 0","data_fine_attivita":"ezdate 0","_NumeroOggetti":"1"},"daone_frontend":{"titolo":"ezstring 0","struttura_di_riferimento":"ezobjectrelationlist 0","utente":"ezobjectrelationlist 0","matricola":"ezstring 0","ruolo":"ezstring 0","descrizione_ruolo_speciale":"ezstring 0","data_inizio_attivita":"ezdate 0","data_fine_attivita":"ezdate 0","_NumeroOggetti":"0"},"dare_frontend":{"titolo":"ezstring 1","struttura_di_riferimento":"ezobjectrelationlist 0","utente":"ezobjectrelationlist 1","matricola":"ezstring 0","ruolo":"ezstring 0","descrizione_ruolo_speciale":"ezstring 0","data_inizio_attivita":"ezdate 0","data_fine_attivita":"ezdate 0","_NumeroOggetti":"1"},"denno_frontend":{"titolo":"ezstring 2","struttura_di_riferimento":"ezobjectrelationlist 2","utente":"ezobjectrelationlist 2","matricola":"ezstring 0","ruolo":"ezstring 0","descrizione_ruolo_speciale":"ezstring 0","data_inizio_attivita":"ezdate 0","data_fine_attivita":"ezdate 0","_NumeroOggetti":"1"},"dimaro_frontend":{"titolo":"ezstring 1","struttura_di_riferimento":"ezobjectrelationlist 0","utente":"ezobjectrelationlist 1","matricola":"ezstring 0","ruolo":"ezstring 0","descrizione_ruolo_speciale":"ezstring 0","data_inizio_attivita":"ezdate 0","data_fine_attivita":"ezdate 0","_NumeroOggetti":"1"},"don_frontend":{"titolo":"ezstring 3","struttura_di_riferimento":"ezobjectrelationlist 2","utente":"ezobjectrelationlist 3","matricola":"ezstring 0","ruolo":"ezstring 0","descrizione_ruolo_speciale":"ezstring 0","data_inizio_attivita":"ezdate 0","data_fine_attivita":"ezdate 0","_NumeroOggetti":"3"},"drena_frontend":{"titolo":"ezstring 3","struttura_di_riferimento":"ezobjectrelationlist 2","utente":"ezobjectrelationlist 3","matricola":"ezstring 0","ruolo":"ezstring 0","descrizione_ruolo_speciale":"ezstring 0","data_inizio_attivita":"ezdate 0","data_fine_attivita":"ezdate 0","_NumeroOggetti":"2"},"dro_frontend":{"titolo":"ezstring 4","struttura_di_riferimento":"ezobjectrelationlist 3","utente":"ezobjectrelationlist 4","matricola":"ezstring 0","ruolo":"ezstring 0","descrizione_ruolo_speciale":"ezstring 0","data_inizio_attivita":"ezdate 0","data_fine_attivita":"ezdate 0","_NumeroOggetti":"3"},"faedo_frontend":{"titolo":"ezstring 4","struttura_di_riferimento":"ezobjectrelationlist 3","utente":"ezobjectrelationlist 4","matricola":"ezstring 0","ruolo":"ezstring 0","descrizione_ruolo_speciale":"ezstring 0","data_inizio_attivita":"ezdate 0","data_fine_attivita":"ezdate 0","_NumeroOggetti":"3"},"fiave_frontend":{"titolo":"ezstring 4","struttura_di_riferimento":"ezobjectrelationlist 3","utente":"ezobjectrelationlist 4","matricola":"ezstring 0","ruolo":"ezstring 0","descrizione_ruolo_speciale":"ezstring 0","data_inizio_attivita":"ezdate 0","data_fine_attivita":"ezdate 0","_NumeroOggetti":"3"},"fierozzo_frontend":{"titolo":"ezstring 10","struttura_di_riferimento":"ezobjectrelationlist 10","utente":"ezobjectrelationlist 10","matricola":"ezstring 0","ruolo":"ezstring 0","descrizione_ruolo_speciale":"ezstring 0","data_inizio_attivita":"ezdate 0","data_fine_attivita":"ezdate 0","_NumeroOggetti":"9"},"forestale_frontend":{"titolo":"ezstring 0","struttura_di_riferimento":"ezobjectrelationlist 0","utente":"ezobjectrelationlist 0","matricola":"ezstring 0","ruolo":"ezstring 0","descrizione_ruolo_speciale":"ezstring 0","data_inizio_attivita":"ezdate 0","data_fine_attivita":"ezdate 0","_NumeroOggetti":"0"},"fornace_frontend":{"titolo":"ezstring 1","struttura_di_riferimento":"ezobjectrelationlist 0","utente":"ezobjectrelationlist 1","matricola":"ezstring 0","ruolo":"ezstring 0","descrizione_ruolo_speciale":"ezstring 0","data_inizio_attivita":"ezdate 0","data_fine_attivita":"ezdate 0","_NumeroOggetti":"1"},"frassilongo_frontend":{"titolo":"ezstring 1","struttura_di_riferimento":"ezobjectrelationlist 0","utente":"ezobjectrelationlist 1","matricola":"ezstring 0","ruolo":"ezstring 0","descrizione_ruolo_speciale":"ezstring 0","data_inizio_attivita":"ezdate 0","data_fine_attivita":"ezdate 0","_NumeroOggetti":"1"},"giustino_frontend":{"titolo":"ezstring 3","struttura_di_riferimento":"ezobjectrelationlist 2","utente":"ezobjectrelationlist 3","matricola":"ezstring 0","ruolo":"ezstring 0","descrizione_ruolo_speciale":"ezstring 0","data_inizio_attivita":"ezdate 0","data_fine_attivita":"ezdate 0","_NumeroOggetti":"2"},"lardaro_frontend":{"titolo":"ezstring 4","struttura_di_riferimento":"ezobjectrelationlist 3","utente":"ezobjectrelationlist 4","matricola":"ezstring 0","ruolo":"ezstring 0","descrizione_ruolo_speciale":"ezstring 0","data_inizio_attivita":"ezdate 0","data_fine_attivita":"ezdate 0","_NumeroOggetti":"4"},"lasino_frontend":{"titolo":"ezstring 1","struttura_di_riferimento":"ezobjectrelationlist 0","utente":"ezobjectrelationlist 1","matricola":"ezstring 0","ruolo":"ezstring 0","descrizione_ruolo_speciale":"ezstring 0","data_inizio_attivita":"ezdate 0","data_fine_attivita":"ezdate 0","_NumeroOggetti":"1"},"lavarone_frontend":{"titolo":"ezstring 2","struttura_di_riferimento":"ezobjectrelationlist 2","utente":"ezobjectrelationlist 2","matricola":"ezstring 0","ruolo":"ezstring 0","descrizione_ruolo_speciale":"ezstring 0","data_inizio_attivita":"ezdate 0","data_fine_attivita":"ezdate 0","_NumeroOggetti":"1"},"ledro_frontend":{"titolo":"ezstring 7","struttura_di_riferimento":"ezobjectrelationlist 6","utente":"ezobjectrelationlist 7","matricola":"ezstring 0","ruolo":"ezstring 0","descrizione_ruolo_speciale":"ezstring 0","data_inizio_attivita":"ezdate 0","data_fine_attivita":"ezdate 0","_NumeroOggetti":"5"},"livo_frontend":{"titolo":"ezstring 4","struttura_di_riferimento":"ezobjectrelationlist 3","utente":"ezobjectrelationlist 4","matricola":"ezstring 0","ruolo":"ezstring 0","descrizione_ruolo_speciale":"ezstring 0","data_inizio_attivita":"ezdate 0","data_fine_attivita":"ezdate 0","_NumeroOggetti":"4"},"luserna_frontend":{"titolo":"ezstring 1","struttura_di_riferimento":"ezobjectrelationlist 0","utente":"ezobjectrelationlist 1","matricola":"ezstring 0","ruolo":"ezstring 0","descrizione_ruolo_speciale":"ezstring 0","data_inizio_attivita":"ezdate 0","data_fine_attivita":"ezdate 0","_NumeroOggetti":"1"},"massimeno_frontend":{"titolo":"ezstring 6","struttura_di_riferimento":"ezobjectrelationlist 5","utente":"ezobjectrelationlist 6","matricola":"ezstring 0","ruolo":"ezstring 0","descrizione_ruolo_speciale":"ezstring 0","data_inizio_attivita":"ezdate 0","data_fine_attivita":"ezdate 0","_NumeroOggetti":"5"},"mazzin_frontend":{"titolo":"ezstring 5","struttura_di_riferimento":"ezobjectrelationlist 4","utente":"ezobjectrelationlist 5","matricola":"ezstring 0","ruolo":"ezstring 0","descrizione_ruolo_speciale":"ezstring 0","data_inizio_attivita":"ezdate 0","data_fine_attivita":"ezdate 0","_NumeroOggetti":"5"},"mezzana_frontend":{"titolo":"ezstring 19","struttura_di_riferimento":"ezobjectrelationlist 18","utente":"ezobjectrelationlist 18","matricola":"ezstring 0","ruolo":"ezstring 0","descrizione_ruolo_speciale":"ezstring 0","data_inizio_attivita":"ezdate 0","data_fine_attivita":"ezdate 0","_NumeroOggetti":"12"},"moena_frontend":{"titolo":"ezstring 2","struttura_di_riferimento":"ezobjectrelationlist 2","utente":"ezobjectrelationlist 2","matricola":"ezstring 0","ruolo":"ezstring 0","descrizione_ruolo_speciale":"ezstring 0","data_inizio_attivita":"ezdate 0","data_fine_attivita":"ezdate 0","_NumeroOggetti":"2"},"mori_frontend":{"titolo":"ezstring 13","struttura_di_riferimento":"ezobjectrelationlist 12","utente":"ezobjectrelationlist 12","matricola":"ezstring 0","ruolo":"ezstring 1","descrizione_ruolo_speciale":"ezstring 0","data_inizio_attivita":"ezdate 0","data_fine_attivita":"ezdate 0","_NumeroOggetti":"10"},"nagotorbole_frontend":{"titolo":"ezstring 3","struttura_di_riferimento":"ezobjectrelationlist 2","utente":"ezobjectrelationlist 3","matricola":"ezstring 0","ruolo":"ezstring 0","descrizione_ruolo_speciale":"ezstring 0","data_inizio_attivita":"ezdate 0","data_fine_attivita":"ezdate 0","_NumeroOggetti":"3"},"nanno_frontend":{"titolo":"ezstring 1","struttura_di_riferimento":"ezobjectrelationlist 0","utente":"ezobjectrelationlist 1","matricola":"ezstring 0","ruolo":"ezstring 0","descrizione_ruolo_speciale":"ezstring 0","data_inizio_attivita":"ezdate 0","data_fine_attivita":"ezdate 0","_NumeroOggetti":"1"},"nave_frontend":{"titolo":"ezstring 1","struttura_di_riferimento":"ezobjectrelationlist 0","utente":"ezobjectrelationlist 1","matricola":"ezstring 0","ruolo":"ezstring 0","descrizione_ruolo_speciale":"ezstring 0","data_inizio_attivita":"ezdate 0","data_fine_attivita":"ezdate 0","_NumeroOggetti":"1"},"nogaredo_frontend":{"titolo":"ezstring 5","struttura_di_riferimento":"ezobjectrelationlist 4","utente":"ezobjectrelationlist 5","matricola":"ezstring 0","ruolo":"ezstring 0","descrizione_ruolo_speciale":"ezstring 0","data_inizio_attivita":"ezdate 0","data_fine_attivita":"ezdate 0","_NumeroOggetti":"4"},"padergnone_frontend":{"titolo":"ezstring 6","struttura_di_riferimento":"ezobjectrelationlist 5","utente":"ezobjectrelationlist 6","matricola":"ezstring 0","ruolo":"ezstring 0","descrizione_ruolo_speciale":"ezstring 0","data_inizio_attivita":"ezdate 0","data_fine_attivita":"ezdate 0","_NumeroOggetti":"5"},"palu_frontend":{"titolo":"ezstring 3","struttura_di_riferimento":"ezobjectrelationlist 2","utente":"ezobjectrelationlist 3","matricola":"ezstring 0","ruolo":"ezstring 0","descrizione_ruolo_speciale":"ezstring 0","data_inizio_attivita":"ezdate 0","data_fine_attivita":"ezdate 0","_NumeroOggetti":"3"},"panchia_frontend":{"titolo":"ezstring 1","struttura_di_riferimento":"ezobjectrelationlist 0","utente":"ezobjectrelationlist 1","matricola":"ezstring 0","ruolo":"ezstring 0","descrizione_ruolo_speciale":"ezstring 0","data_inizio_attivita":"ezdate 0","data_fine_attivita":"ezdate 0","_NumeroOggetti":"1"},"pellizzano_frontend":{"titolo":"ezstring 10","struttura_di_riferimento":"ezobjectrelationlist 10","utente":"ezobjectrelationlist 10","matricola":"ezstring 0","ruolo":"ezstring 0","descrizione_ruolo_speciale":"ezstring 0","data_inizio_attivita":"ezdate 0","data_fine_attivita":"ezdate 0","_NumeroOggetti":"10"},"pelugo_frontend":{"titolo":"ezstring 1","struttura_di_riferimento":"ezobjectrelationlist 0","utente":"ezobjectrelationlist 1","matricola":"ezstring 0","ruolo":"ezstring 0","descrizione_ruolo_speciale":"ezstring 0","data_inizio_attivita":"ezdate 0","data_fine_attivita":"ezdate 0","_NumeroOggetti":"1"},"pievedibono_frontend":{"titolo":"ezstring 0","struttura_di_riferimento":"ezobjectrelationlist 0","utente":"ezobjectrelationlist 0","matricola":"ezstring 0","ruolo":"ezstring 0","descrizione_ruolo_speciale":"ezstring 0","data_inizio_attivita":"ezdate 0","data_fine_attivita":"ezdate 0","_NumeroOggetti":"0"},"pomarolo_frontend":{"titolo":"ezstring 5","struttura_di_riferimento":"ezobjectrelationlist 4","utente":"ezobjectrelationlist 5","matricola":"ezstring 0","ruolo":"ezstring 0","descrizione_ruolo_speciale":"ezstring 0","data_inizio_attivita":"ezdate 0","data_fine_attivita":"ezdate 0","_NumeroOggetti":"2"},"praso_frontend":{"titolo":"ezstring 0","struttura_di_riferimento":"ezobjectrelationlist 0","utente":"ezobjectrelationlist 0","matricola":"ezstring 0","ruolo":"ezstring 0","descrizione_ruolo_speciale":"ezstring 0","data_inizio_attivita":"ezdate 0","data_fine_attivita":"ezdate 0","_NumeroOggetti":"0"},"predazzo_frontend":{"titolo":"ezstring 1","struttura_di_riferimento":"ezobjectrelationlist 0","utente":"ezobjectrelationlist 1","matricola":"ezstring 0","ruolo":"ezstring 0","descrizione_ruolo_speciale":"ezstring 0","data_inizio_attivita":"ezdate 0","data_fine_attivita":"ezdate 0","_NumeroOggetti":"1"},"preore_frontend":{"titolo":"ezstring 1","struttura_di_riferimento":"ezobjectrelationlist 0","utente":"ezobjectrelationlist 1","matricola":"ezstring 0","ruolo":"ezstring 0","descrizione_ruolo_speciale":"ezstring 0","data_inizio_attivita":"ezdate 0","data_fine_attivita":"ezdate 0","_NumeroOggetti":"1"},"prezzo_frontend":{"titolo":"ezstring 4","struttura_di_riferimento":"ezobjectrelationlist 3","utente":"ezobjectrelationlist 4","matricola":"ezstring 0","ruolo":"ezstring 0","descrizione_ruolo_speciale":"ezstring 0","data_inizio_attivita":"ezdate 0","data_fine_attivita":"ezdate 0","_NumeroOggetti":"4"},"prototipo_frontend":{"titolo":"ezstring 0","struttura_di_riferimento":"ezobjectrelationlist 0","utente":"ezobjectrelationlist 0","matricola":"ezstring 0","ruolo":"ezstring 0","descrizione_ruolo_speciale":"ezstring 0","data_inizio_attivita":"ezdate 0","data_fine_attivita":"ezdate 0","_NumeroOggetti":"0"},"rabbi_frontend":{"titolo":"ezstring 3","struttura_di_riferimento":"ezobjectrelationlist 2","utente":"ezobjectrelationlist 3","matricola":"ezstring 0","ruolo":"ezstring 0","descrizione_ruolo_speciale":"ezstring 0","data_inizio_attivita":"ezdate 0","data_fine_attivita":"ezdate 0","_NumeroOggetti":"2"},"ricadi_frontend":{"titolo":"ezstring 7","struttura_di_riferimento":"ezobjectrelationlist 6","utente":"ezobjectrelationlist 7","matricola":"ezstring 0","ruolo":"ezstring 0","descrizione_ruolo_speciale":"ezstring 0","data_inizio_attivita":"ezdate 0","data_fine_attivita":"ezdate 0","_NumeroOggetti":"5"},"rivadelgarda_frontend":{"titolo":"ezstring 0","struttura_di_riferimento":"ezobjectrelationlist 0","utente":"ezobjectrelationlist 0","matricola":"ezstring 0","ruolo":"ezstring 0","descrizione_ruolo_speciale":"ezstring 0","data_inizio_attivita":"ezdate 0","data_fine_attivita":"ezdate 0","_NumeroOggetti":"0"},"roncone_frontend":{"titolo":"ezstring 0","struttura_di_riferimento":"ezobjectrelationlist 0","utente":"ezobjectrelationlist 0","matricola":"ezstring 0","ruolo":"ezstring 0","descrizione_ruolo_speciale":"ezstring 0","data_inizio_attivita":"ezdate 0","data_fine_attivita":"ezdate 0","_NumeroOggetti":"0"},"ronzo_frontend":{"titolo":"ezstring 1","struttura_di_riferimento":"ezobjectrelationlist 0","utente":"ezobjectrelationlist 1","matricola":"ezstring 0","ruolo":"ezstring 0","descrizione_ruolo_speciale":"ezstring 0","data_inizio_attivita":"ezdate 0","data_fine_attivita":"ezdate 0","_NumeroOggetti":"1"},"ronzone_frontend":{"titolo":"ezstring 1","struttura_di_riferimento":"ezobjectrelationlist 0","utente":"ezobjectrelationlist 1","matricola":"ezstring 0","ruolo":"ezstring 0","descrizione_ruolo_speciale":"ezstring 0","data_inizio_attivita":"ezdate 0","data_fine_attivita":"ezdate 0","_NumeroOggetti":"1"},"roveredellaluna_frontend":{"titolo":"ezstring 5","struttura_di_riferimento":"ezobjectrelationlist 4","utente":"ezobjectrelationlist 5","matricola":"ezstring 0","ruolo":"ezstring 0","descrizione_ruolo_speciale":"ezstring 0","data_inizio_attivita":"ezdate 0","data_fine_attivita":"ezdate 0","_NumeroOggetti":"5"},"rumo_frontend":{"titolo":"ezstring 2","struttura_di_riferimento":"ezobjectrelationlist 1","utente":"ezobjectrelationlist 2","matricola":"ezstring 0","ruolo":"ezstring 0","descrizione_ruolo_speciale":"ezstring 0","data_inizio_attivita":"ezdate 0","data_fine_attivita":"ezdate 0","_NumeroOggetti":"1"},"samone_frontend":{"titolo":"ezstring 4","struttura_di_riferimento":"ezobjectrelationlist 3","utente":"ezobjectrelationlist 4","matricola":"ezstring 0","ruolo":"ezstring 0","descrizione_ruolo_speciale":"ezstring 0","data_inizio_attivita":"ezdate 0","data_fine_attivita":"ezdate 0","_NumeroOggetti":"4"},"santorsola_frontend":{"titolo":"ezstring 2","struttura_di_riferimento":"ezobjectrelationlist 1","utente":"ezobjectrelationlist 2","matricola":"ezstring 0","ruolo":"ezstring 0","descrizione_ruolo_speciale":"ezstring 0","data_inizio_attivita":"ezdate 0","data_fine_attivita":"ezdate 0","_NumeroOggetti":"2"},"sanzeno_frontend":{"titolo":"ezstring 4","struttura_di_riferimento":"ezobjectrelationlist 3","utente":"ezobjectrelationlist 4","matricola":"ezstring 0","ruolo":"ezstring 0","descrizione_ruolo_speciale":"ezstring 0","data_inizio_attivita":"ezdate 0","data_fine_attivita":"ezdate 0","_NumeroOggetti":"4"},"soraga_frontend":{"titolo":"ezstring 13","struttura_di_riferimento":"ezobjectrelationlist 13","utente":"ezobjectrelationlist 13","matricola":"ezstring 0","ruolo":"ezstring 0","descrizione_ruolo_speciale":"ezstring 0","data_inizio_attivita":"ezdate 0","data_fine_attivita":"ezdate 0","_NumeroOggetti":"7"},"spera_frontend":{"titolo":"ezstring 5","struttura_di_riferimento":"ezobjectrelationlist 4","utente":"ezobjectrelationlist 5","matricola":"ezstring 0","ruolo":"ezstring 0","descrizione_ruolo_speciale":"ezstring 0","data_inizio_attivita":"ezdate 0","data_fine_attivita":"ezdate 0","_NumeroOggetti":"5"},"spiazzo_frontend":{"titolo":"ezstring 9","struttura_di_riferimento":"ezobjectrelationlist 8","utente":"ezobjectrelationlist 9","matricola":"ezstring 0","ruolo":"ezstring 0","descrizione_ruolo_speciale":"ezstring 0","data_inizio_attivita":"ezdate 0","data_fine_attivita":"ezdate 0","_NumeroOggetti":"8"},"spormaggiore_frontend":{"titolo":"ezstring 1","struttura_di_riferimento":"ezobjectrelationlist 0","utente":"ezobjectrelationlist 1","matricola":"ezstring 0","ruolo":"ezstring 0","descrizione_ruolo_speciale":"ezstring 0","data_inizio_attivita":"ezdate 0","data_fine_attivita":"ezdate 0","_NumeroOggetti":"1"},"stenico_frontend":{"titolo":"ezstring 2","struttura_di_riferimento":"ezobjectrelationlist 2","utente":"ezobjectrelationlist 2","matricola":"ezstring 0","ruolo":"ezstring 0","descrizione_ruolo_speciale":"ezstring 0","data_inizio_attivita":"ezdate 0","data_fine_attivita":"ezdate 0","_NumeroOggetti":"2"},"storo_frontend":{"titolo":"ezstring 11","struttura_di_riferimento":"ezobjectrelationlist 10","utente":"ezobjectrelationlist 11","matricola":"ezstring 0","ruolo":"ezstring 0","descrizione_ruolo_speciale":"ezstring 0","data_inizio_attivita":"ezdate 0","data_fine_attivita":"ezdate 0","_NumeroOggetti":"11"},"strembo_frontend":{"titolo":"ezstring 6","struttura_di_riferimento":"ezobjectrelationlist 5","utente":"ezobjectrelationlist 6","matricola":"ezstring 0","ruolo":"ezstring 0","descrizione_ruolo_speciale":"ezstring 0","data_inizio_attivita":"ezdate 0","data_fine_attivita":"ezdate 0","_NumeroOggetti":"6"},"strigno_frontend":{"titolo":"ezstring 6","struttura_di_riferimento":"ezobjectrelationlist 5","utente":"ezobjectrelationlist 6","matricola":"ezstring 0","ruolo":"ezstring 0","descrizione_ruolo_speciale":"ezstring 0","data_inizio_attivita":"ezdate 0","data_fine_attivita":"ezdate 0","_NumeroOggetti":"6"},"tassullo_frontend":{"titolo":"ezstring 1","struttura_di_riferimento":"ezobjectrelationlist 0","utente":"ezobjectrelationlist 1","matricola":"ezstring 0","ruolo":"ezstring 0","descrizione_ruolo_speciale":"ezstring 0","data_inizio_attivita":"ezdate 0","data_fine_attivita":"ezdate 0","_NumeroOggetti":"1"},"telvedisopra_frontend":{"titolo":"ezstring 5","struttura_di_riferimento":"ezobjectrelationlist 4","utente":"ezobjectrelationlist 5","matricola":"ezstring 0","ruolo":"ezstring 0","descrizione_ruolo_speciale":"ezstring 0","data_inizio_attivita":"ezdate 0","data_fine_attivita":"ezdate 0","_NumeroOggetti":"5"},"tenna_frontend":{"titolo":"ezstring 7","struttura_di_riferimento":"ezobjectrelationlist 5","utente":"ezobjectrelationlist 7","matricola":"ezstring 0","ruolo":"ezstring 0","descrizione_ruolo_speciale":"ezstring 0","data_inizio_attivita":"ezdate 0","data_fine_attivita":"ezdate 0","_NumeroOggetti":"4"},"terzolas_frontend":{"titolo":"ezstring 5","struttura_di_riferimento":"ezobjectrelationlist 4","utente":"ezobjectrelationlist 5","matricola":"ezstring 0","ruolo":"ezstring 0","descrizione_ruolo_speciale":"ezstring 0","data_inizio_attivita":"ezdate 0","data_fine_attivita":"ezdate 0","_NumeroOggetti":"5"},"tesero_frontend":{"titolo":"ezstring 10","struttura_di_riferimento":"ezobjectrelationlist 9","utente":"ezobjectrelationlist 10","matricola":"ezstring 0","ruolo":"ezstring 0","descrizione_ruolo_speciale":"ezstring 0","data_inizio_attivita":"ezdate 0","data_fine_attivita":"ezdate 0","_NumeroOggetti":"9"},"torcegno_frontend":{"titolo":"ezstring 5","struttura_di_riferimento":"ezobjectrelationlist 4","utente":"ezobjectrelationlist 5","matricola":"ezstring 0","ruolo":"ezstring 0","descrizione_ruolo_speciale":"ezstring 0","data_inizio_attivita":"ezdate 0","data_fine_attivita":"ezdate 0","_NumeroOggetti":"5"},"tres_frontend":{"titolo":"ezstring 1","struttura_di_riferimento":"ezobjectrelationlist 0","utente":"ezobjectrelationlist 1","matricola":"ezstring 0","ruolo":"ezstring 0","descrizione_ruolo_speciale":"ezstring 0","data_inizio_attivita":"ezdate 0","data_fine_attivita":"ezdate 0","_NumeroOggetti":"1"},"varena_frontend":{"titolo":"ezstring 5","struttura_di_riferimento":"ezobjectrelationlist 4","utente":"ezobjectrelationlist 5","matricola":"ezstring 0","ruolo":"ezstring 0","descrizione_ruolo_speciale":"ezstring 0","data_inizio_attivita":"ezdate 0","data_fine_attivita":"ezdate 0","_NumeroOggetti":"5"},"vattaro_frontend":{"titolo":"ezstring 2","struttura_di_riferimento":"ezobjectrelationlist 2","utente":"ezobjectrelationlist 2","matricola":"ezstring 0","ruolo":"ezstring 0","descrizione_ruolo_speciale":"ezstring 0","data_inizio_attivita":"ezdate 0","data_fine_attivita":"ezdate 0","_NumeroOggetti":"2"},"vignolafalesina_frontend":{"titolo":"ezstring 1","struttura_di_riferimento":"ezobjectrelationlist 0","utente":"ezobjectrelationlist 1","matricola":"ezstring 0","ruolo":"ezstring 0","descrizione_ruolo_speciale":"ezstring 0","data_inizio_attivita":"ezdate 0","data_fine_attivita":"ezdate 0","_NumeroOggetti":"1"},"vigolovattaro_frontend":{"titolo":"ezstring 1","struttura_di_riferimento":"ezobjectrelationlist 1","utente":"ezobjectrelationlist 1","matricola":"ezstring 0","ruolo":"ezstring 0","descrizione_ruolo_speciale":"ezstring 0","data_inizio_attivita":"ezdate 0","data_fine_attivita":"ezdate 0","_NumeroOggetti":"1"},"vigorendena_frontend":{"titolo":"ezstring 0","struttura_di_riferimento":"ezobjectrelationlist 0","utente":"ezobjectrelationlist 0","matricola":"ezstring 0","ruolo":"ezstring 0","descrizione_ruolo_speciale":"ezstring 0","data_inizio_attivita":"ezdate 0","data_fine_attivita":"ezdate 0","_NumeroOggetti":"0"},"villaagnedo_frontend":{"titolo":"ezstring 6","struttura_di_riferimento":"ezobjectrelationlist 4","utente":"ezobjectrelationlist 6","matricola":"ezstring 0","ruolo":"ezstring 0","descrizione_ruolo_speciale":"ezstring 0","data_inizio_attivita":"ezdate 0","data_fine_attivita":"ezdate 0","_NumeroOggetti":"6"},"zambana_frontend":{"titolo":"ezstring 6","struttura_di_riferimento":"ezobjectrelationlist 5","utente":"ezobjectrelationlist 6","matricola":"ezstring 0","ruolo":"ezstring 0","descrizione_ruolo_speciale":"ezstring 0","data_inizio_attivita":"ezdate 0","data_fine_attivita":"ezdate 0","_NumeroOggetti":"6"},"zianofiemme_frontend":{"titolo":"ezstring 2","struttura_di_riferimento":"ezobjectrelationlist 1","utente":"ezobjectrelationlist 2","matricola":"ezstring 0","ruolo":"ezstring 0","descrizione_ruolo_speciale":"ezstring 0","data_inizio_attivita":"ezdate 0","data_fine_attivita":"ezdate 0","_NumeroOggetti":"2"}}